jfExt/CommonExt.py
jfExt/CurrencyExt.py
jfExt/EncryptExt.py
jfExt/GeoExt.py
jfExt/ImageExt.py
jfExt/IpExt.py
jfExt/OrderExt.py
jfExt/PrintExt.py
jfExt/RequestExt.py
jfExt/SingletonExt.py
jfExt/ThumbnailExt.py
jfExt/ValidExt.py
jfExt/__init__.py
jfExt/cacheExt.py
jfExt/debugExt.py
jfExt/dirExt.py
jfExt/fileExt.py
jfExt/macosExt.py
jfExt/phpPassExt.py
jfExt/BasicType/BooleanExt.py
jfExt/BasicType/DictExt.py
jfExt/BasicType/FloatExt.py
jfExt/BasicType/JsonExt.py
jfExt/BasicType/ListExt.py
jfExt/BasicType/StringExt.py
jfExt/BasicType/__init__.py
jfExt/Math/__init__.py
jfExt/Math/binConversionExt.py
jfExt/Math/coordinateExt.py
jfExt/Mgr/__init__.py
jfExt/Mgr/mailMgr.py
jfExt/Mgr/redisMgr.py
jfExt/Mgr/responseMgr.py
jfExt/Time/DateExt.py
jfExt/Time/TimeExt.py
jfExt/Time/__init__.py
jfExt/data/Inconsolata.otf
jfext-1.45.0.dist-info/METADATA
jfext-1.45.0.dist-info/WHEEL
jfext-1.45.0.dist-info/top_level.txt
jfext-1.45.0.dist-info/zip-safe
jfext-1.45.0.dist-info/RECORD
