Metadata-Version: 2.4
Name: jfExt
Version: 1.45.0
Summary: private common python framework
Home-page: http://www.jifu.nz
Author: jifu
Author-email: ji.fu@icloud.com
License: MIT
Keywords: jfExt
Requires-Dist: flask
Requires-Dist: flask_mail
Requires-Dist: flask_redis
Requires-Dist: six
Requires-Dist: prettytable
Requires-Dist: requests
Requires-Dist: uuid
Requires-Dist: validators
Requires-Dist: geoip2
Requires-Dist: icecream
Requires-Dist: urllib3
Requires-Dist: xlwt
Requires-Dist: check-digit-EAN13
Requires-Dist: numpy
Requires-Dist: requests
Requires-Dist: xlsxwriter
Requires-Dist: pillow
Requires-Dist: fake_useragent
Dynamic: author
Dynamic: author-email
Dynamic: description
Dynamic: home-page
Dynamic: keywords
Dynamic: license
Dynamic: requires-dist
Dynamic: summary
